<wws-history>
  <raid dpstime="100" start="1215448481828" dps="20695" comment="Shade of Akama" lg="7811220" dmg="2694264" dir="sws-akama-1215477281">
    <player dmgout="10.9042395251542" heal="0" name="Shaelak" pres="100" dmgin="0" ovh="0" dps="2276" dpstime="99.1955867381452" classe="rog" decurse="0" death="0" />
    <player dmgout="9.38196850791162" heal="0" name="Yoshiriko" pres="100" dmgin="0" ovh="0" dps="1965" dpstime="99.2892311940865" classe="rog" decurse="0" death="0" />
    <player dmgout="8.78529349759341" heal="0" name="Painez" pres="100" dmgin="0" ovh="0" dps="1856" dpstime="98.8140425577183" classe="rog" decurse="0" death="0" />
    <player dmgout="8.18939792091644" heal="0" name="Turion" pres="100" dmgin="0" ovh="0" dps="1749" dpstime="97.2655105223316" classe="war" decurse="0" death="0" />
    <player dmgout="8.13699028751451" heal="0" name="Apocalypsed" pres="100" dmgin="0" ovh="0" dps="1723" dpstime="97.7552775010791" classe="rog" decurse="0" death="0" />
    <player dmgout="7.70477577549936" heal="0" name="Iruga" pres="100" dmgin="0" ovh="0" dps="1751" dpstime="94.0736802000457" classe="rog" decurse="0" death="0" />
    <player dmgout="6.42769231226042" heal="0" name="Nekrosis" pres="100" dmgin="0" ovh="0" dps="1394" dpstime="96.4108056149695" classe="sha" decurse="0" death="0" />
    <player dmgout="6.36633974992799" heal="0" name="Korrick" pres="100" dmgin="0" ovh="0" dps="1329" dpstime="99.4822086799405" classe="war" decurse="0" death="0" />
    <player dmgout="5.58237797038449" heal="2.70226957487608" name="Hadessa" pres="100" dmgin="11.8070944247039" ovh="96" dps="1407" dpstime="92.1603449459734" classe="pri" decurse="0" death="0" />
    <player dmgout="5.39765219740901" heal="0" name="Jackk" pres="100" dmgin="2.01482103680944" ovh="0" dps="1672" dpstime="79.1160535795898" classe="mag" decurse="0" death="0" />
    <player dmgout="4.6168081524305" heal="0" name="Evinald" pres="100" dmgin="1.18645660066645" ovh="0" dps="1547" dpstime="73.1360927279361" classe="mag" decurse="0" death="0" />
    <player dmgout="4.06830956431886" heal="0" name="Fearsalot" pres="100" dmgin="1.81974922496256" ovh="0" dps="1771" dpstime="48.2702172857072" classe="wrl" decurse="0" death="0" />
    <player dmgout="3.27647921658754" heal="0" name="Wylan" pres="100" dmgin="0" ovh="0" dps="1334" dpstime="52.8611117373492" classe="wrl" decurse="0" death="0" />
    <player dmgout="2.33470068263541" heal="7.07674114025829" name="Riggz" pres="100" dmgin="20.8091335606408" ovh="53" dps="746" dpstime="65.0412331656454" classe="drd" decurse="0" death="0" />
    <player dmgout="2.18401017866104" heal="0" name="Jesi" pres="100" dmgin="1.95955990030891" ovh="0" dps="878" dpstime="53.5977864595569" classe="mag" decurse="0" death="0" />
    <player dmgout="2.07043556236508" heal="4.04345735774402" name="Dilldar" pres="100" dmgin="42.9506131223095" ovh="60" dps="475" dpstime="90.6629037882044" classe="drd" decurse="0" death="0" />
    <player dmgout="1.24657420356728" heal="5.67808177542979" name="Dernus" pres="100" dmgin="0" ovh="64" dps="1199" dpstime="22.3756620391586" classe="sha" decurse="0" death="0" />
    <player dmgout="1.10200782105985" heal="0" name="Jamor" pres="100" dmgin="12.749296802038" ovh="0" dps="340" dpstime="72.1072575955055" classe="war" decurse="0" death="0" />
    <player dmgout="0.738346353586731" heal="0.612293392425909" name="Gwai" pres="100" dmgin="0" ovh="98" dps="338" dpstime="47.5794347818373" classe="sha" decurse="0" death="0" />
    <player dmgout="0.589140485119498" heal="8.07696771091794" name="Naomil" pres="100" dmgin="2.36020313993778" ovh="73" dps="390" dpstime="31.8069220767098" classe="pri" decurse="0" death="0" />
    <player dmgout="0.443237930655645" heal="0" name="Dratine" pres="100" dmgin="0" ovh="0" dps="232" dpstime="39.8994311646074" classe="sha" decurse="0" death="0" />
    <player dmgout="0.428614270910349" heal="13.680446952072" name="Cyder" pres="100" dmgin="0.392906680518792" ovh="64" dps="408" dpstime="26.4960618243203" classe="pal" decurse="0" death="0" />
    <player dmgout="0.0246078335307899" heal="13.5130057084754" name="Milledius" pres="100" dmgin="0" ovh="55" dps="0" dpstime="0" classe="pri" decurse="0" death="0" />
    <player dmgout="0" heal="7.63543123027868" name="Hateorade" pres="100" dmgin="1.95016550710382" ovh="80" dps="0" dpstime="0" classe="pal" decurse="0" death="0" />
    <player dmgout="0" heal="36.9813051575219" name="Tahonaa" pres="100" dmgin="0" ovh="16" dps="0" dpstime="0" classe="drd" decurse="0" death="0" />
  </raid>
  <raid dpstime="100" start="1215450321578" dps="17305" comment="Gurtogg Bloodboil" lg="19739039" dmg="5693345" dir="sws-bloodboil-1215479121">
    <player dmgout="9.13733490592964" heal="0" name="Shaelak" pres="100" dmgin="0" ovh="0" dps="1604" dpstime="100" classe="rog" decurse="0" death="0" />
    <player dmgout="8.51848956983987" heal="0" name="Yoshiriko" pres="100" dmgin="0.218452956199399" ovh="0" dps="1507" dpstime="100" classe="rog" decurse="0" death="0" />
    <player dmgout="8.09311573424762" heal="0" name="Apocalypsed" pres="100" dmgin="0.720111458005509" ovh="0" dps="1431" dpstime="100" classe="rog" decurse="0" death="0" />
    <player dmgout="7.80114326463617" heal="0" name="Painez" pres="100" dmgin="0" ovh="0" dps="1362" dpstime="100" classe="rog" decurse="0" death="0" />
    <player dmgout="7.4140597487066" heal="0.269451744456103" name="Wylan" pres="100" dmgin="5.34187974678256" ovh="60" dps="1535" dpstime="83.715481357277" classe="wrl" decurse="0" death="0" />
    <player dmgout="7.13858021953702" heal="0" name="Evinald" pres="100" dmgin="3.69904388972286" ovh="0" dps="1304" dpstime="98.2862960305599" classe="mag" decurse="0" death="1" />
    <player dmgout="7.04784270055653" heal="0.530059419719424" name="Fearsalot" pres="100" dmgin="3.54659679885478" ovh="62" dps="1609" dpstime="78.50154858116" classe="wrl" decurse="0" death="0" />
    <player dmgout="6.58837642897102" heal="0" name="Jackk" pres="100" dmgin="6.26310717737196" ovh="0" dps="1242" dpstime="95.859841255441" classe="mag" decurse="0" death="1" />
    <player dmgout="6.00601228276172" heal="0.114680533582429" name="Nekrosis" pres="100" dmgin="0.602756093009784" ovh="35" dps="1093" dpstime="96.3032475846938" classe="sha" decurse="0" death="0" />
    <player dmgout="5.97316691681252" heal="0.0836166541862963" name="Iruga" pres="100" dmgin="2.34526219924859" ovh="0" dps="1087" dpstime="96.3161651852437" classe="rog" decurse="0" death="0" />
    <player dmgout="5.77558535447966" heal="4.97782221739818" name="Hadessa" pres="100" dmgin="5.98818717815178" ovh="35" dps="1149" dpstime="89.7383566944423" classe="pri" decurse="0" death="1" />
    <player dmgout="5.74038636337689" heal="0" name="Jesi" pres="100" dmgin="4.98598419758313" ovh="0" dps="1039" dpstime="98.4891111261561" classe="mag" decurse="0" death="0" />
    <player dmgout="5.6229334424666" heal="0" name="Turion" pres="100" dmgin="1.05090667550458" ovh="0" dps="1006" dpstime="98.698002961405" classe="war" decurse="0" death="0" />
    <player dmgout="4.03439454310252" heal="0" name="Korrick" pres="100" dmgin="0.946815147371323" ovh="0" dps="1091" dpstime="96.3948580369228" classe="war" decurse="0" death="1" />
    <player dmgout="2.43986619465358" heal="0.872017913260147" name="Riggz" pres="100" dmgin="10.1309603714153" ovh="43" dps="448" dpstime="94.5255140811545" classe="drd" decurse="0" death="0" />
    <player dmgout="1.92872555589025" heal="0.28220620787875" name="Dilldar" pres="100" dmgin="6.64187501218463" ovh="77" dps="367" dpstime="91.2194825379997" classe="drd" decurse="0" death="0" />
    <player dmgout="0.468705128531645" heal="0.071008373725513" name="Jamor" pres="100" dmgin="5.95187698957553" ovh="0" dps="415" dpstime="88.1601445748819" classe="war" decurse="0" death="1" />
    <player dmgout="0.175661232544313" heal="11.414733122903" name="Dratine" pres="100" dmgin="2.22449513868194" ovh="46" dps="93" dpstime="33.0494537923278" classe="sha" decurse="0" death="0" />
    <player dmgout="0.0600525701498855" heal="15.7956172155289" name="Naomil" pres="100" dmgin="3.92693122857246" ovh="46" dps="252" dpstime="4.1707318884576" classe="pri" decurse="0" death="0" />
    <player dmgout="0.0355678428059427" heal="9.37412861250076" name="Milledius" pres="100" dmgin="2.12931579489722" ovh="34" dps="135" dpstime="4.59050473456652" classe="pri" decurse="0" death="0" />
    <player dmgout="0" heal="9.78183289313989" name="Hateorade" pres="100" dmgin="2.89468443904762" ovh="38" dps="0" dpstime="0" classe="pal" decurse="0" death="0" />
    <player dmgout="0" heal="10.8428653760904" name="Dernus" pres="100" dmgin="12.3343935119298" ovh="47" dps="0" dpstime="0" classe="sha" decurse="0" death="0" />
    <player dmgout="0" heal="8.31382704435959" name="Cyder" pres="100" dmgin="2.08691329280146" ovh="42" dps="0" dpstime="0" classe="pal" decurse="0" death="0" />
    <player dmgout="0" heal="16.02468591677" name="Tahonaa" pres="100" dmgin="11.6582859641452" ovh="16" dps="0" dpstime="0" classe="drd" decurse="0" death="0" />
    <player dmgout="0" heal="11.2514467545007" name="Gwai" pres="100" dmgin="4.31116473894263" ovh="49" dps="0" dpstime="0" classe="sha" decurse="0" death="0" />
  </raid>
  <raid dpstime="100" start="1215454882796" dps="18222" comment="Illidari Council" lg="24032819" dmg="7299129" dir="sws-council-1215483682">
    <player dmgout="9.85836803267897" heal="0.00785097880876618" name="Shaelak" pres="100" dmgin="3.31861137155488" ovh="89" dps="2031" dpstime="100" classe="rog" decurse="0" death="1" />
    <player dmgout="9.25462476413282" heal="0.356538583555244" name="Iruga" pres="100" dmgin="4.17463042664856" ovh="14" dps="1732" dpstime="98.1529181691981" classe="rog" decurse="0" death="0" />
    <player dmgout="9.20952349246054" heal="0.280712548427721" name="Apocalypsed" pres="100" dmgin="3.97826265508749" ovh="23" dps="1762" dpstime="100" classe="rog" decurse="0" death="0" />
    <player dmgout="9.02095304795956" heal="0.126857397384503" name="Painez" pres="100" dmgin="3.70491903450065" ovh="36" dps="1696" dpstime="99.269149368631" classe="rog" decurse="0" death="0" />
    <player dmgout="8.85178217839416" heal="0.295493217715654" name="Sepo" pres="100" dmgin="0.655564421445154" ovh="84" dps="1723" dpstime="94.2959145282815" classe="wrl" decurse="0" death="0" />
    <player dmgout="8.2957843326238" heal="0.498416986313661" name="Korrick" pres="100" dmgin="4.02782081768191" ovh="7" dps="1547" dpstime="97.9249355540347" classe="war" decurse="0" death="0" />
    <player dmgout="6.82915728712289" heal="0.89092587073764" name="Nekrosis" pres="100" dmgin="3.07427256830714" ovh="11" dps="1315" dpstime="99.3489447152303" classe="sha" decurse="0" death="0" />
    <player dmgout="6.65008112611792" heal="0.138914257697965" name="Wylan" pres="100" dmgin="0.955532163009454" ovh="85" dps="1524" dpstime="79.6167757995956" classe="wrl" decurse="0" death="0" />
    <player dmgout="6.50721476493976" heal="0" name="Evinald" pres="100" dmgin="1.08139164399384" ovh="0" dps="1217" dpstime="98.8800506036141" classe="mag" decurse="0" death="0" />
    <player dmgout="6.34326369625746" heal="0" name="Jesi" pres="100" dmgin="1.16431923392365" ovh="0" dps="1217" dpstime="97.1864622975979" classe="mag" decurse="0" death="0" />
    <player dmgout="5.27395802978684" heal="3.62723232167864" name="Hadessa" pres="100" dmgin="3.66770081471397" ovh="77" dps="998" dpstime="98.7404226137009" classe="pri" decurse="0" death="0" />
    <player dmgout="3.70845617333246" heal="0.25503664324191" name="Turion" pres="100" dmgin="3.36979634332975" ovh="5" dps="731" dpstime="94.9334188288353" classe="war" decurse="0" death="0" />
    <player dmgout="3.44413696483512" heal="0.0665730958171908" name="Jackk" pres="100" dmgin="11.0902359309773" ovh="0" dps="779" dpstime="80.6266333309365" classe="mag" decurse="0" death="0" />
    <player dmgout="3.00109780221722" heal="1.42491259777673" name="Jamor" pres="100" dmgin="26.3181618167253" ovh="15" dps="552" dpstime="99.4840444036308" classe="war" decurse="0" death="0" />
    <player dmgout="1.69820262116206" heal="0.940835664593367" name="Riggz" pres="100" dmgin="5.85437042286325" ovh="24" dps="513" dpstime="60.48996715867" classe="drd" decurse="0" death="0" />
    <player dmgout="1.09360993619924" heal="0.091648160788046" name="Yoshiriko" pres="100" dmgin="2.16115647880724" ovh="0" dps="311" dpstime="65.7619694335791" classe="rog" decurse="0" death="0" />
    <player dmgout="0.909300274046397" heal="1.39178627392546" name="Dilldar" pres="100" dmgin="14.2740998884644" ovh="36" dps="212" dpstime="78.4381601440509" classe="drd" decurse="0" death="0" />
    <player dmgout="0.0284554499584813" heal="12.7189061183159" name="Naomil" pres="100" dmgin="0.139151702336773" ovh="46" dps="149" dpstime="3.50966274035212" classe="pri" decurse="0" death="0" />
    <player dmgout="0.0142619756412032" heal="7.75720767921862" name="Milledius" pres="100" dmgin="0" ovh="47" dps="77" dpstime="3.45189216768883" classe="pri" decurse="0" death="0" />
    <player dmgout="0.00402787784679514" heal="13.0721200526817" name="Gwai" pres="100" dmgin="1.09853265779751" ovh="39" dps="4" dpstime="21.2458039539217" classe="sha" decurse="0" death="0" />
    <player dmgout="0.00374017228630978" heal="7.77114717220561" name="Dernus" pres="100" dmgin="1.05103776538317" ovh="52" dps="4" dpstime="21.4097704188973" classe="sha" decurse="0" death="0" />
    <player dmgout="0" heal="9.9354136824936" name="Hateorade" pres="100" dmgin="2.0444626788151" ovh="54" dps="0" dpstime="2.4995063475202" classe="pal" decurse="0" death="0" />
    <player dmgout="0" heal="13.5543143531915" name="Dratine" pres="100" dmgin="1.13170369376944" ovh="43" dps="0" dpstime="0" classe="sha" decurse="0" death="0" />
    <player dmgout="0" heal="9.65990841592883" name="Cyder" pres="100" dmgin="0.595174090405357" ovh="53" dps="0" dpstime="0" classe="pal" decurse="0" death="0" />
    <player dmgout="0" heal="15.1372479275018" name="Tahonaa" pres="100" dmgin="1.0690913794588" ovh="10" dps="0" dpstime="0" classe="drd" decurse="0" death="0" />
  </raid>
  <raid dpstime="100" start="1215456073640" dps="10626" comment="Illidan Stormrage try 1" lg="38615639" dmg="6839320" dir="sws-illidan-1215484873">
    <player dmgout="10.2667516653702" heal="0.165069792741898" name="Wylan" pres="100" dmgin="0.947713585443324" ovh="94" dps="1668" dpstime="83.9280732815413" classe="wrl" decurse="0" death="1" />
    <player dmgout="9.09240977173169" heal="0.236211703936576" name="Fearsalot" pres="100" dmgin="0.936679817176267" ovh="92" dps="1941" dpstime="65.6310214182121" classe="wrl" decurse="0" death="0" />
    <player dmgout="8.336691366978" heal="0.166440377424757" name="Shaelak" pres="100" dmgin="2.40797474312371" ovh="32" dps="1255" dpstime="83.8726641160678" classe="rog" decurse="0" death="1" />
    <player dmgout="7.15383985542422" heal="1.74274125502726" name="Hadessa" pres="100" dmgin="25.3709596445733" ovh="88" dps="1282" dpstime="59.3986389216527" classe="pri" decurse="0" death="1" />
    <player dmgout="6.75630033395133" heal="0.186442347640239" name="Yoshiriko" pres="100" dmgin="3.03684146188138" ovh="62" dps="1228" dpstime="61.0104820980852" classe="rog" decurse="0" death="0" />
    <player dmgout="6.73656152950878" heal="0" name="Jesi" pres="100" dmgin="1.66058212419203" ovh="0" dps="1075" dpstime="82.9586621100565" classe="mag" decurse="0" death="1" />
    <player dmgout="6.6907236391922" heal="0.243621427378286" name="Korrick" pres="100" dmgin="2.52031592582172" ovh="24" dps="1099" dpstime="81.6099203173201" classe="war" decurse="0" death="1" />
    <player dmgout="6.47361141166081" heal="0.392458357782565" name="Painez" pres="100" dmgin="3.22316696443323" ovh="69" dps="1043" dpstime="74.1704059968813" classe="rog" decurse="0" death="1" />
    <player dmgout="6.10353076036799" heal="0.0832201887123785" name="Jackk" pres="100" dmgin="1.04141350701646" ovh="0" dps="1199" dpstime="57.1054499315411" classe="mag" decurse="0" death="1" />
    <player dmgout="5.7653684869256" heal="0.265636443846717" name="Apocalypsed" pres="100" dmgin="2.71845917491223" ovh="24" dps="1284" dpstime="56.6316663078735" classe="rog" decurse="0" death="1" />
    <player dmgout="5.32514928384693" heal="0.163099577260287" name="Sepo" pres="100" dmgin="2.27983785006445" ovh="89" dps="955" dpstime="59.7614145411826" classe="wrl" decurse="0" death="0" />
    <player dmgout="5.20812010550757" heal="0.734719051555399" name="Nekrosis" pres="100" dmgin="3.29085042188194" ovh="20" dps="1135" dpstime="61.9364222260342" classe="sha" decurse="0" death="1" />
    <player dmgout="4.93464262529023" heal="0" name="Evinald" pres="100" dmgin="0.681973987600948" ovh="0" dps="1352" dpstime="89.2968286364182" classe="mag" decurse="0" death="0" />
    <player dmgout="4.72169747869671" heal="0.361577371646886" name="Turion" pres="100" dmgin="2.53898622317887" ovh="56" dps="827" dpstime="72.881204075565" classe="war" decurse="0" death="1" />
    <player dmgout="2.26291502664008" heal="2.4469219666177" name="Jamor" pres="100" dmgin="15.4261952692428" ovh="36" dps="469" dpstime="61.1491285525293" classe="war" decurse="0" death="1" />
    <player dmgout="1.96095518267898" heal="0.731763728332984" name="Dilldar" pres="100" dmgin="11.4005539532395" ovh="54" dps="368" dpstime="65.5429749910787" classe="drd" decurse="0" death="1" />
    <player dmgout="1.83630828795845" heal="1.03316386624807" name="Riggz" pres="100" dmgin="7.29346600568588" ovh="56" dps="493" dpstime="46.8063315661537" classe="drd" decurse="0" death="1" />
    <player dmgout="0.204450150014914" heal="12.36832750121" name="Gwai" pres="100" dmgin="2.30585431418887" ovh="45" dps="177" dpstime="14.9966972170163" classe="sha" decurse="0" death="1" />
    <player dmgout="0.0778878601966277" heal="9.31924772033219" name="Dratine" pres="100" dmgin="1.42129453395831" ovh="56" dps="132" dpstime="7.58548963467368" classe="sha" decurse="0" death="1" />
    <player dmgout="0.0451799301684963" heal="9.54008317735794" name="Hateorade" pres="100" dmgin="1.01693596320296" ovh="63" dps="103" dpstime="5.61026603915575" classe="pal" decurse="0" death="1" />
    <player dmgout="0.0428258949720148" heal="11.6758824209665" name="Naomil" pres="100" dmgin="2.61183812997373" ovh="54" dps="229" dpstime="2.20234293915896" classe="pri" decurse="0" death="1" />
    <player dmgout="0.00407935291812636" heal="11.3969684380046" name="Dernus" pres="100" dmgin="1.43793229505574" ovh="60" dps="0" dpstime="0" classe="sha" decurse="0" death="1" />
    <player dmgout="0" heal="11.6752399593964" name="Milledius" pres="100" dmgin="0.998788318026883" ovh="48" dps="0" dpstime="0" classe="pri" decurse="0" death="1" />
    <player dmgout="0" heal="11.9876904363171" name="Cyder" pres="100" dmgin="1.42469177313527" ovh="56" dps="0" dpstime="0" classe="pal" decurse="0" death="1" />
    <player dmgout="0" heal="13.0834728902633" name="Tahonaa" pres="100" dmgin="2.00669401299023" ovh="22" dps="0" dpstime="0" classe="drd" decurse="0" death="1" />
  </raid>
  <raid dpstime="100" start="1215445833578" dps="24212" comment="High Warlord Naj'entus" lg="9706859" dmg="3917103" dir="sws-najentus-1215474633">
    <player dmgout="7.68647135395725" heal="0.548986610728481" name="Wylan" pres="100" dmgin="4.2260884761226" dps="2086" ovh="51" dpstime="89.838071441894" classe="wrl" decurse="0" death="0" />
    <player dmgout="7.43960523887169" heal="0" name="Evinald" pres="100" dmgin="2.56173621807578" ovh="0" dps="1837" dpstime="98.7165210053524" classe="mag" decurse="0" death="0" />
    <player dmgout="7.40838318522643" heal="0.398574282360348" name="Apocalypsed" pres="100" dmgin="3.78183756101048" ovh="9" dps="1871" dpstime="97.1628586207132" classe="rog" decurse="0" death="0" />
    <player dmgout="7.28929006972755" heal="0.845177538033357" name="Fearsalot" pres="100" dmgin="4.0836133370595" ovh="36" dps="2119" dpstime="84.0055857540465" classe="wrl" decurse="0" death="0" />
    <player dmgout="7.15470080822485" heal="0.265225846501461" name="Yoshiriko" pres="100" dmgin="7.42921556351337" ovh="16" dps="1793" dpstime="97.6000798535228" classe="rog" decurse="0" death="0" />
    <player dmgout="6.80880742732576" heal="0.182260024301337" name="Korrick" pres="100" dmgin="6.10245645048429" ovh="19" dps="1694" dpstime="97.8445116358771" classe="war" decurse="0" death="0" />
    <player dmgout="6.51851636273031" heal="0.237717674956384" name="Iruga" pres="100" dmgin="4.84812641220448" ovh="41" dps="1623" dpstime="99.8014476159781" classe="rog" decurse="0" death="0" />
    <player dmgout="6.47338096547372" heal="0" name="Jackk" pres="100" dmgin="2.80307018399007" ovh="0" dps="1633" dpstime="98.0947205142174" classe="mag" decurse="0" death="0" />
    <player dmgout="6.00811364929643" heal="0.0349368488874636" name="Shaelak" pres="100" dmgin="2.43045400681541" ovh="59" dps="1482" dpstime="100" classe="rog" decurse="0" death="0" />
    <player dmgout="5.94773739674448" heal="0.0838484373299127" name="Painez" pres="100" dmgin="2.61365696059295" ovh="40" dps="1470" dpstime="99.7639891498427" classe="rog" decurse="0" death="0" />
    <player dmgout="5.73102111432862" heal="0.98529268988729" name="Nekrosis" pres="100" dmgin="7.80991953368097" ovh="6" dps="1411" dpstime="99.0372646556663" classe="sha" decurse="0" death="0" />
    <player dmgout="5.72323474772045" heal="0" name="Jesi" pres="100" dmgin="2.04837800033651" ovh="0" dps="1452" dpstime="96.7693030134065" classe="mag" decurse="0" death="0" />
    <player dmgout="5.46018320171821" heal="6.44765062562702" name="Hadessa" pres="100" dmgin="5.87318196162198" ovh="59" dps="1342" dpstime="99.0386645902225" classe="pri" decurse="0" death="0" />
    <player dmgout="4.41433375635004" heal="0.0209621093324782" name="Turion" pres="100" dmgin="2.67872036672364" ovh="40" dps="1122" dpstime="97.8393946383175" classe="war" decurse="0" death="0" />
    <player dmgout="4.13101212809569" heal="0.386438324325756" name="Dilldar" pres="100" dmgin="2.74089527535686" ovh="69" dps="1065" dpstime="96.5937759349654" classe="drd" decurse="0" death="0" />
    <player dmgout="3.48637756015096" heal="0.524788245920112" name="Riggz" pres="100" dmgin="5.81707289773347" ovh="58" dps="873" dpstime="96.9247050347338" classe="drd" decurse="0" death="0" />
    <player dmgout="2.24158006567609" heal="0.479554220518448" name="Jamor" pres="100" dmgin="15.1262670574804" ovh="11" dps="547" dpstime="99.5354253644319" classe="war" decurse="0" death="0" />
    <player dmgout="0.0620101130861251" heal="10.8930152780679" name="Naomil" pres="100" dmgin="2.37391166830228" ovh="53" dps="162" dpstime="9.58593998477407" classe="pri" decurse="0" death="0" />
    <player dmgout="0.0152408552953548" heal="11.0504149762135" name="Milledius" pres="100" dmgin="2.79368256712327" ovh="47" dps="81" dpstime="4.66632026493241" classe="pri" decurse="0" death="0" />
    <player dmgout="0" heal="7.85071447694756" name="Hateorade" pres="100" dmgin="2.24544574210195" ovh="60" dps="0" dpstime="0" classe="pal" decurse="0" death="0" />
    <player dmgout="0" heal="10.8321148341125" name="Dernus" pres="100" dmgin="2.08116244693288" ovh="52" dps="0" dpstime="0" classe="sha" decurse="0" death="0" />
    <player dmgout="0" heal="13.4106013845289" name="Dratine" pres="100" dmgin="1.87102425399136" ovh="51" dps="0" dpstime="0" classe="sha" decurse="0" death="0" />
    <player dmgout="0" heal="8.35115725553768" name="Cyder" pres="100" dmgin="1.41767457176219" ovh="44" dps="0" dpstime="0" classe="pal" decurse="0" death="0" />
    <player dmgout="0" heal="10.5591661052254" name="Tahonaa" pres="100" dmgin="1.99840699363014" ovh="12" dps="0" dpstime="0" classe="drd" decurse="0" death="0" />
    <player dmgout="0" heal="15.6114022106567" name="Gwai" pres="100" dmgin="2.24400149335321" ovh="47" dps="0" dpstime="0" classe="sha" decurse="0" death="0" />
  </raid>
  <raid dpstime="100" start="1215449331703" dps="24770" comment="Reliquary of Souls" lg="21415319" dmg="8841078" dir="sws-ros-1215478131">
    <player dmgout="7.65036797548896" heal="1.42718462562432" name="Wylan" pres="100" dmgin="6.08747049709207" ovh="31" dps="2237" dpstime="84.7879425166491" classe="wrl" decurse="0" death="0" />
    <player dmgout="7.06235144628291" heal="0" name="Evinald" pres="100" dmgin="5.04871679073226" ovh="0" dps="1971" dpstime="88.8907594502053" classe="mag" decurse="0" death="0" />
    <player dmgout="6.92127136532446" heal="0.0309817679672124" name="Shaelak" pres="100" dmgin="5.86393352106007" ovh="84" dps="1928" dpstime="89.8605052889881" classe="rog" decurse="0" death="0" />
    <player dmgout="6.75837267808292" heal="0" name="Jackk" pres="100" dmgin="4.9113676295432" ovh="0" dps="1939" dpstime="86.560674195879" classe="mag" decurse="0" death="0" />
    <player dmgout="6.62625078073058" heal="0.0829552644346586" name="Painez" pres="100" dmgin="6.03326865868896" ovh="60" dps="1926" dpstime="86.8560321516146" classe="rog" decurse="0" death="0" />
    <player dmgout="6.33513243520756" heal="0.133622046878998" name="Iruga" pres="100" dmgin="5.48825032249486" ovh="64" dps="1876" dpstime="85.0536797668891" classe="rog" decurse="0" death="0" />
    <player dmgout="6.24455524541238" heal="0.167470155283993" name="Yoshiriko" pres="100" dmgin="5.78366453075478" ovh="43" dps="1922" dpstime="82.8287981356687" classe="rog" decurse="0" death="0" />
    <player dmgout="6.18362376171774" heal="1.3363047729205" name="Fearsalot" pres="100" dmgin="4.53645468896577" ovh="42" dps="1922" dpstime="80.1203869103915" classe="wrl" decurse="0" death="0" />
    <player dmgout="6.04238532902888" heal="0.352728482108345" name="Korrick" pres="100" dmgin="5.53000641341125" ovh="27" dps="1770" dpstime="85.1897001182381" classe="war" decurse="0" death="0" />
    <player dmgout="5.90710770790621" heal="0.0185890607803275" name="Apocalypsed" pres="100" dmgin="5.09099990027186" ovh="25" dps="1835" dpstime="81.8219702205819" classe="rog" decurse="0" death="0" />
    <player dmgout="5.78274504534402" heal="0" name="Jesi" pres="100" dmgin="4.51991441217559" ovh="0" dps="1733" dpstime="83.1300961868851" classe="mag" decurse="0" death="1" />
    <player dmgout="5.43150959645419" heal="1.44552077401308" name="Nekrosis" pres="100" dmgin="3.3628652948507" ovh="9" dps="1634" dpstime="84.2336419343936" classe="sha" decurse="0" death="0" />
    <player dmgout="5.33794634545697" heal="0.114611465446055" name="Turion" pres="100" dmgin="4.77709950030527" ovh="81" dps="1555" dpstime="86.4919234720444" classe="war" decurse="0" death="0" />
    <player dmgout="4.94281353472959" heal="8.47956236039763" name="Hadessa" pres="100" dmgin="4.95438045717649" ovh="58" dps="1422" dpstime="86.3811798310012" classe="pri" decurse="0" death="0" />
    <player dmgout="3.94384033259293" heal="0.485633943877897" name="Riggz" pres="100" dmgin="4.12919091290166" ovh="66" dps="1142" dpstime="86.2520513314161" classe="drd" decurse="0" death="0" />
    <player dmgout="3.93024470545334" heal="0.61799142879905" name="Dilldar" pres="100" dmgin="4.29860713031873" ovh="50" dps="1326" dpstime="74.1297526410106" classe="drd" decurse="0" death="0" />
    <player dmgout="1.96875313168824" heal="0.678521794514583" name="Jamor" pres="100" dmgin="10.7033428385872" ovh="40" dps="586" dpstime="83.2283569839263" classe="war" decurse="0" death="0" />
    <player dmgout="0.832194897500056" heal="10.3995889330596" name="Gwai" pres="100" dmgin="1.11484708757347" ovh="72" dps="397" dpstime="52.0756696769179" classe="sha" decurse="0" death="0" />
    <player dmgout="0.649717149876972" heal="10.3182354471048" name="Dratine" pres="100" dmgin="1.23622353048965" ovh="72" dps="607" dpstime="26.5385413052696" classe="sha" decurse="0" death="0" />
    <player dmgout="0.433114604350284" heal="9.98253639936216" name="Dernus" pres="100" dmgin="1.11484708757347" ovh="68" dps="531" dpstime="20.2862359834521" classe="sha" decurse="0" death="0" />
    <player dmgout="0.369502452076545" heal="16.1038593166391" name="Tahonaa" pres="100" dmgin="1.32520859802506" ovh="48" dps="425" dpstime="21.6775725092655" classe="drd" decurse="0" death="0" />
    <player dmgout="0.323716180311948" heal="8.45574644352487" name="Milledius" pres="100" dmgin="1.15238702950412" ovh="61" dps="524" dpstime="15.4729853822929" classe="pri" decurse="0" death="0" />
    <player dmgout="0.196684160008542" heal="5.58089128855913" name="Cyder" pres="100" dmgin="1.04795626231906" ovh="73" dps="287" dpstime="17.1970204091679" classe="pal" decurse="0" death="0" />
    <player dmgout="0.0922625046402712" heal="17.3408116717383" name="Naomil" pres="100" dmgin="1.092550145822" ovh="54" dps="285" dpstime="8.04943824082278" classe="pri" decurse="0" death="0" />
    <player dmgout="0.0335366343335055" heal="6.44665255696535" name="Hateorade" pres="100" dmgin="0.796446759362486" ovh="72" dps="259" dpstime="3.21558125593043" classe="pal" decurse="0" death="0" />
  </raid>
  <raid dpstime="100" start="1215453541265" dps="15099" comment="Mother Shahraz try 1" lg="5137500" dmg="1292921" dir="sws-shahraz-1215482341">
    <player dmgout="8.63919759985336" heal="0" name="Yoshiriko" pres="100" dmgin="1.64349562755705" ovh="0" dps="1864" dpstime="82.8366149480685" classe="rog" decurse="0" death="0" />
    <player dmgout="8.33330110656413" heal="0.640320608080689" name="Korrick" pres="100" dmgin="5.53409729897427" ovh="0" dps="1536" dpstime="96.1858015489428" classe="war" decurse="0" death="1" />
    <player dmgout="8.21248939417026" heal="0" name="Iruga" pres="100" dmgin="0.914431970216974" ovh="0" dps="1444" dpstime="97.7585862832814" classe="rog" decurse="0" death="0" />
    <player dmgout="7.80991259326749" heal="1.31898209173264" name="Nekrosis" pres="100" dmgin="2.94592131541698" ovh="1" dps="1680" dpstime="78.6694935235751" classe="sha" decurse="0" death="0" />
    <player dmgout="7.54222415754714" heal="0" name="Painez" pres="100" dmgin="1.15506175712097" ovh="0" dps="1427" dpstime="91.8944707063975" classe="rog" decurse="0" death="0" />
    <player dmgout="7.3046999778022" heal="0" name="Wylan" pres="100" dmgin="2.1109883078355" ovh="0" dps="1613" dpstime="75.6919495423723" classe="wrl" decurse="0" death="0" />
    <player dmgout="7.13315043997274" heal="0" name="Jesi" pres="100" dmgin="8.58724526399473" ovh="0" dps="1235" dpstime="95.5828172988203" classe="mag" decurse="0" death="1" />
    <player dmgout="6.64719654178407" heal="0" name="Jackk" pres="100" dmgin="6.50185174412968" ovh="0" dps="1224" dpstime="95.1536001715653" classe="mag" decurse="0" death="1" />
    <player dmgout="6.51965587998029" heal="1.68028187540055" name="Fearsalot" pres="100" dmgin="4.65010761444942" ovh="34" dps="1091" dpstime="95.558686308148" classe="wrl" decurse="0" death="0" />
    <player dmgout="5.95279990038061" heal="7.30351700571755" name="Hadessa" pres="100" dmgin="5.35512768308999" ovh="65" dps="988" dpstime="96.162720522992" classe="pri" decurse="0" death="1" />
    <player dmgout="5.84761172569708" heal="0" name="Evinald" pres="100" dmgin="3.90805266321525" ovh="0" dps="1282" dpstime="82.4817213283476" classe="mag" decurse="0" death="0" />
    <player dmgout="5.1399892182121" heal="0" name="Apocalypsed" pres="100" dmgin="1.62875923448316" ovh="0" dps="970" dpstime="95.8087680472844" classe="rog" decurse="0" death="0" />
    <player dmgout="4.6103358209821" heal="0" name="Turion" pres="100" dmgin="1.24231671611114" ovh="0" dps="811" dpstime="96.25662852036" classe="war" decurse="0" death="0" />
    <player dmgout="3.78236566657978" heal="2.38049261028599" name="Jamor" pres="100" dmgin="16.1617513039769" ovh="0" dps="735" dpstime="99.6959532832995" classe="war" decurse="0" death="1" />
    <player dmgout="3.71213709112931" heal="0" name="Shaelak" pres="100" dmgin="1.45424931650282" ovh="0" dps="1520" dpstime="55.7480897337678" classe="rog" decurse="0" death="0" />
    <player dmgout="1.86801823158569" heal="0.902829668561322" name="Riggz" pres="100" dmgin="5.36967017625502" ovh="66" dps="305" dpstime="94.5311012372316" classe="drd" decurse="0" death="0" />
    <player dmgout="0.781331574009549" heal="1.12643813265943" name="Dilldar" pres="100" dmgin="2.37760068252768" ovh="17" dps="338" dpstime="36.073328770938" classe="drd" decurse="0" death="0" />
    <player dmgout="0.153528328490294" heal="14.1049644437355" name="Milledius" pres="100" dmgin="3.87062998080391" ovh="37" dps="133" dpstime="17.9295522775223" classe="pri" decurse="0" death="0" />
    <player dmgout="0.0100547519918077" heal="8.76410846269881" name="Dratine" pres="100" dmgin="4.85971341593469" ovh="59" dps="11" dpstime="14.8199095805126" classe="sha" decurse="0" death="0" />
    <player dmgout="0" heal="5.59189076488647" name="Hateorade" pres="100" dmgin="2.46504954142672" ovh="59" dps="0" dpstime="0" classe="pal" decurse="0" death="0" />
    <player dmgout="0" heal="13.7187570839665" name="Naomil" pres="100" dmgin="3.50726155158707" ovh="39" dps="0" dpstime="8.134554400779" classe="pri" decurse="0" death="0" />
    <player dmgout="0" heal="14.1964787963764" name="Dernus" pres="100" dmgin="2.78731118996374" ovh="58" dps="0" dpstime="8.37017756809227" classe="sha" decurse="0" death="0" />
    <player dmgout="0" heal="7.47115338868972" name="Cyder" pres="100" dmgin="3.46324627227425" ovh="64" dps="0" dpstime="0" classe="pal" decurse="0" death="0" />
    <player dmgout="0" heal="9.05152509928048" name="Tahonaa" pres="100" dmgin="4.64215771818587" ovh="11" dps="0" dpstime="16.4496002197266" classe="drd" decurse="0" death="1" />
    <player dmgout="0" heal="11.748259967928" name="Gwai" pres="100" dmgin="2.86390165396622" ovh="58" dps="0" dpstime="0" classe="sha" decurse="0" death="0" />
  </raid>
  <raid dpstime="100" start="1215453777078" dps="20290" comment="Mother Shahraz" lg="13464359" dmg="4553358" dir="sws-shahraz-1215482577">
    <player dmgout="8.5478233866083" heal="0.139480040224457" name="Yoshiriko" pres="100" dmgin="2.80766857250283" ovh="0" dps="1787" dpstime="99.7925586405657" classe="rog" decurse="0" death="0" />
    <player dmgout="8.26853500207978" heal="0.189058253574383" name="Korrick" pres="100" dmgin="3.34067604735846" ovh="0" dps="1716" dpstime="98.3893525258148" classe="war" decurse="0" death="0" />
    <player dmgout="8.15973617712466" heal="0.139480040224457" name="Shaelak" pres="100" dmgin="2.01359287579643" ovh="0" dps="1686" dpstime="100" classe="rog" decurse="0" death="0" />
    <player dmgout="7.32977727646278" heal="0.524124345464296" name="Fearsalot" pres="100" dmgin="2.94261648555093" ovh="77" dps="1587" dpstime="94.1469505486645" classe="wrl" decurse="0" death="0" />
    <player dmgout="7.05786806132968" heal="1.48123175418461" name="Nekrosis" pres="100" dmgin="4.35519663897142" ovh="3" dps="1478" dpstime="99.3505929290915" classe="sha" decurse="0" death="0" />
    <player dmgout="6.64538127685106" heal="0" name="Painez" pres="100" dmgin="1.90921462930192" ovh="0" dps="1380" dpstime="100" classe="rog" decurse="0" death="0" />
    <player dmgout="6.52749026103372" heal="0" name="Iruga" pres="100" dmgin="1.61348988708023" ovh="0" dps="1353" dpstime="100" classe="rog" decurse="0" death="0" />
    <player dmgout="6.50390327314479" heal="0" name="Evinald" pres="100" dmgin="1.41061846358818" ovh="0" dps="1364" dpstime="99.0525605175746" classe="mag" decurse="0" death="0" />
    <player dmgout="6.43735897770393" heal="0.406458719113806" name="Wylan" pres="100" dmgin="2.71023797749778" ovh="67" dps="1373" dpstime="95.7213787208948" classe="wrl" decurse="0" death="0" />
    <player dmgout="6.43716132138084" heal="0" name="Apocalypsed" pres="100" dmgin="2.26346311818773" ovh="0" dps="1349" dpstime="99.3570292355602" classe="rog" decurse="0" death="0" />
    <player dmgout="5.92947007461307" heal="0" name="Jackk" pres="100" dmgin="2.72691234107247" ovh="0" dps="1252" dpstime="98.8965852065902" classe="mag" decurse="0" death="0" />
    <player dmgout="5.58800779556538" heal="0" name="Jesi" pres="100" dmgin="3.10437415964068" ovh="0" dps="1177" dpstime="98.7870429601559" classe="mag" decurse="0" death="0" />
    <player dmgout="4.92943888883764" heal="6.07341376572146" name="Hadessa" pres="100" dmgin="3.71691180978148" ovh="69" dps="1043" dpstime="96.0663523877919" classe="pri" decurse="0" death="0" />
    <player dmgout="3.9333169058967" heal="0.280612687560578" name="Turion" pres="100" dmgin="2.368495261293" ovh="19" dps="836" dpstime="98.7690152263833" classe="war" decurse="0" death="0" />
    <player dmgout="3.25219321652284" heal="1.97329552168262" name="Jamor" pres="100" dmgin="28.0154646548448" ovh="31" dps="661" dpstime="100" classe="war" decurse="0" death="0" />
    <player dmgout="2.21537599283869" heal="0.533957357778698" name="Riggz" pres="100" dmgin="7.82043999068197" ovh="71" dps="459" dpstime="98.4474439881971" classe="drd" decurse="0" death="0" />
    <player dmgout="2.19363379729861" heal="0.820932582719183" name="Dilldar" pres="100" dmgin="6.65773007965278" ovh="65" dps="484" dpstime="93.0022685414272" classe="drd" decurse="0" death="0" />
    <player dmgout="0.04045366079276" heal="8.25188046031719" name="Naomil" pres="100" dmgin="1.50551520922648" ovh="62" dps="137" dpstime="6.06534958318805" classe="pri" decurse="0" death="0" />
    <player dmgout="0.00307465391475917" heal="6.70512283415509" name="Hateorade" pres="100" dmgin="2.21482955776155" ovh="72" dps="5" dpstime="15.5963425878251" classe="pal" decurse="0" death="0" />
    <player dmgout="0" heal="9.86639497805751" name="Milledius" pres="100" dmgin="3.17891837326871" ovh="44" dps="0" dpstime="9.43902696744339" classe="pri" decurse="0" death="0" />
    <player dmgout="0" heal="14.4545281021708" name="Dernus" pres="100" dmgin="2.15679623355552" ovh="57" dps="0" dpstime="0" classe="sha" decurse="0" death="0" />
    <player dmgout="0" heal="10.1883228434097" name="Dratine" pres="100" dmgin="3.66182102032392" ovh="57" dps="0" dpstime="7.20135292044621" classe="sha" decurse="0" death="0" />
    <player dmgout="0" heal="7.60034010654358" name="Cyder" pres="100" dmgin="3.77044959478844" ovh="69" dps="0" dpstime="7.71812234884468" classe="pal" decurse="0" death="0" />
    <player dmgout="0" heal="11.117088040165" name="Tahonaa" pres="100" dmgin="2.51161688197575" ovh="10" dps="0" dpstime="3.94697742300345" classe="drd" decurse="0" death="0" />
    <player dmgout="0" heal="19.2542775669327" name="Gwai" pres="100" dmgin="1.22295013629657" ovh="36" dps="0" dpstime="0" classe="sha" decurse="0" death="0" />
  </raid>
  <raid dpstime="100" start="1215446821765" dps="16077" comment="Supremus" lg="16998779" dmg="4554852" dir="sws-supremus-1215475621">
    <player dmgout="8.89133170517944" heal="0.350481236604681" name="Wylan" pres="100" dmgin="3.2827770689518" ovh="92" dps="2013" dpstime="85.9429641307843" classe="wrl" decurse="0" death="1" />
    <player dmgout="8.45342505091274" heal="0.248293073945003" name="Shaelak" pres="100" dmgin="2.78577168044813" ovh="72" dps="1402" dpstime="99.1373587400541" classe="rog" decurse="0" death="0" />
    <player dmgout="8.01071033702083" heal="0.887715248918426" name="Fearsalot" pres="100" dmgin="2.39838473248736" ovh="83" dps="1766" dpstime="74.314813544728" classe="wrl" decurse="0" death="0" />
    <player dmgout="7.75298516834356" heal="0.325182915389907" name="Yoshiriko" pres="100" dmgin="2.118049048476" ovh="59" dps="1733" dpstime="74.6678732746612" classe="rog" decurse="0" death="0" />
    <player dmgout="7.46342581493318" heal="0" name="Painez" pres="100" dmgin="2.09725491806856" ovh="0" dps="1454" dpstime="85.4086014990663" classe="rog" decurse="0" death="0" />
    <player dmgout="7.1152696070037" heal="0.325182915389907" name="Apocalypsed" pres="100" dmgin="2.6526635740746" ovh="45" dps="1437" dpstime="81.9979573631367" classe="rog" decurse="0" death="0" />
    <player dmgout="6.24112484884251" heal="3.36680860256622" name="Hadessa" pres="100" dmgin="8.51789193726847" ovh="92" dps="1190" dpstime="94.1296934086289" classe="pri" decurse="0" death="1" />
    <player dmgout="6.01870269330376" heal="0" name="Jackk" pres="100" dmgin="1.35059160584597" ovh="0" dps="997" dpstime="98.7106033099455" classe="mag" decurse="0" death="0" />
    <player dmgout="5.85575557669053" heal="0.506392800495733" name="Iruga" pres="100" dmgin="7.30913683821396" ovh="40" dps="1324" dpstime="88.4796613563518" classe="rog" decurse="0" death="1" />
    <player dmgout="5.32467355690152" heal="0" name="Jesi" pres="100" dmgin="0" ovh="0" dps="898" dpstime="97.6847887586102" classe="mag" decurse="0" death="0" />
    <player dmgout="5.16767613964186" heal="0.241613180141102" name="Korrick" pres="100" dmgin="3.29291741649616" ovh="61" dps="1230" dpstime="68.5442495892014" classe="war" decurse="0" death="0" />
    <player dmgout="4.79580895273875" heal="0" name="Evinald" pres="100" dmgin="1.42401285642038" ovh="0" dps="787" dpstime="98.8707966606349" classe="mag" decurse="0" death="0" />
    <player dmgout="4.34861549837404" heal="0" name="Turion" pres="100" dmgin="0.243111623405462" ovh="0" dps="762" dpstime="95.4231789015007" classe="war" decurse="0" death="0" />
    <player dmgout="4.01854988921704" heal="0.441725743457968" name="Nekrosis" pres="100" dmgin="4.17397242338903" ovh="60" dps="1159" dpstime="58.1615595132584" classe="sha" decurse="0" death="1" />
    <player dmgout="3.95841621198669" heal="4.02172244614869" name="Riggz" pres="100" dmgin="27.9709292922551" ovh="52" dps="642" dpstime="99.4419535722733" classe="drd" decurse="0" death="0" />
    <player dmgout="3.7867750697498" heal="0.0746158350435756" name="Dilldar" pres="100" dmgin="0.445918574292807" ovh="97" dps="892" dpstime="69.1633625739205" classe="drd" decurse="0" death="0" />
    <player dmgout="2.29243452915704" heal="3.80384420782144" name="Jamor" pres="100" dmgin="19.8668662218605" ovh="35" dps="377" dpstime="98.0286479261247" classe="war" decurse="0" death="0" />
    <player dmgout="0.246791772817207" heal="6.89365040562589" name="Dratine" pres="100" dmgin="1.53696862653485" ovh="73" dps="66" dpstime="61.5424168190691" classe="sha" decurse="0" death="0" />
    <player dmgout="0.169423726610656" heal="15.4703497990347" name="Gwai" pres="100" dmgin="3.37006107313116" ovh="45" dps="464" dpstime="5.88973721127638" classe="sha" decurse="0" death="0" />
    <player dmgout="0.0816931044082223" heal="11.2750922393847" name="Naomil" pres="100" dmgin="0.22937722863018" ovh="74" dps="186" dpstime="7.10122728853904" classe="pri" decurse="0" death="0" />
    <player dmgout="0.00476415040488692" heal="10.7708313198902" name="Hateorade" pres="100" dmgin="1.53555667940842" ovh="74" dps="19" dpstime="4.18851533992544" classe="pal" decurse="0" death="0" />
    <player dmgout="0.00164659576205769" heal="8.74938175450964" name="Cyder" pres="100" dmgin="0" ovh="59" dps="0" dpstime="0" classe="pal" decurse="0" death="0" />
    <player dmgout="0" heal="11.166082057521" name="Milledius" pres="100" dmgin="1.92474065098464" ovh="46" dps="0" dpstime="0" classe="pri" decurse="0" death="0" />
    <player dmgout="0" heal="8.63525505824299" name="Dernus" pres="100" dmgin="1.02340494900304" ovh="65" dps="0" dpstime="0" classe="sha" decurse="0" death="0" />
    <player dmgout="0" heal="12.4457791598683" name="Tahonaa" pres="100" dmgin="0.449640980353398" ovh="27" dps="0" dpstime="0" classe="drd" decurse="0" death="0" />
  </raid>
  <raid dpstime="100" start="1215451900984" dps="27308" comment="Teron Gorefiend" lg="11007180" dmg="5009867" dir="sws-teron-1215480700">
    <player dmgout="8.66442163035466" heal="0.106258795584515" name="Apocalypsed" pres="100" dmgin="2.87877335888836" ovh="61" dps="2430" dpstime="99.738148221935" classe="rog" decurse="0" death="0" />
    <player dmgout="8.59603658141024" heal="0.00965989050768317" name="Shaelak" pres="100" dmgin="2.08586487781505" ovh="97" dps="2394" dpstime="99.0286345826777" classe="rog" decurse="0" death="0" />
    <player dmgout="7.77304068151909" heal="0" name="Evinald" pres="100" dmgin="1.67858169621466" ovh="0" dps="2216" dpstime="96.3591501760189" classe="mag" decurse="0" death="0" />
    <player dmgout="7.5741332055322" heal="0.736693755033311" name="Jackk" pres="100" dmgin="2.86804024916148" ovh="5" dps="2149" dpstime="97.0462001785941" classe="mag" decurse="0" death="0" />
    <player dmgout="7.41676375839918" heal="0.643043658637772" name="Fearsalot" pres="100" dmgin="3.88193579300431" ovh="76" dps="2194" dpstime="93.6503110462497" classe="wrl" decurse="0" death="0" />
    <player dmgout="7.25478341041788" heal="0.211907492821176" name="Yoshiriko" pres="100" dmgin="2.70071873502635" ovh="61" dps="2047" dpstime="99.7108511617557" classe="rog" decurse="0" death="0" />
    <player dmgout="7.20096960657838" heal="0.00223702727546347" name="Iruga" pres="100" dmgin="1.54844274077623" ovh="99" dps="2023" dpstime="97.6142270131248" classe="rog" decurse="0" death="0" />
    <player dmgout="6.42460169102294" heal="0.178860498979102" name="Korrick" pres="100" dmgin="4.25999041686632" ovh="37" dps="1798" dpstime="98.1579653564173" classe="war" decurse="0" death="0" />
    <player dmgout="6.25850945743669" heal="0" name="Painez" pres="100" dmgin="1.97527551509344" ovh="0" dps="1965" dpstime="96.8154798036223" classe="rog" decurse="0" death="0" />
    <player dmgout="6.21118285176034" heal="0.833496026226094" name="Nekrosis" pres="100" dmgin="4.38629611883086" ovh="16" dps="1744" dpstime="99.8076203280854" classe="sha" decurse="0" death="0" />
    <player dmgout="5.36116028629103" heal="0.202247602313493" name="Turion" pres="100" dmgin="2.76387158600862" ovh="13" dps="1490" dpstime="99.5770876287509" classe="war" decurse="0" death="0" />
    <player dmgout="4.92639824570193" heal="0.559256818865868" name="Riggz" pres="100" dmgin="4.20450407283182" ovh="67" dps="1386" dpstime="98.3773603859715" classe="drd" decurse="0" death="0" />
    <player dmgout="4.48215491548977" heal="3.12014463398166" name="Hadessa" pres="100" dmgin="6.80459990416866" ovh="83" dps="1505" dpstime="99.8427442182358" classe="pri" decurse="0" death="1" />
    <player dmgout="3.94349790124169" heal="0.316437676420106" name="Dilldar" pres="100" dmgin="1.7396262577863" ovh="79" dps="1132" dpstime="97.0392268722213" classe="drd" decurse="0" death="0" />
    <player dmgout="2.81111255049286" heal="2.34694666113511" name="Jamor" pres="100" dmgin="29.7494010541447" ovh="26" dps="773" dpstime="99.6238834235255" classe="war" decurse="0" death="0" />
    <player dmgout="2.45230062993688" heal="0" name="Wylan" pres="100" dmgin="2.34873023478678" ovh="0" dps="2282" dpstime="45.2588487899528" classe="wrl" decurse="0" death="1" />
    <player dmgout="2.14099496054486" heal="0" name="Jesi" pres="100" dmgin="1.50359367513177" ovh="0" dps="1492" dpstime="94.0525552597653" classe="mag" decurse="0" death="1" />
    <player dmgout="0.232880433752034" heal="18.3006117252768" name="Gwai" pres="100" dmgin="3.52208912314327" ovh="54" dps="86" dpstime="75.0602475550676" classe="sha" decurse="0" death="0" />
    <player dmgout="0.181441942470728" heal="20.2787539351343" name="Dratine" pres="100" dmgin="3.47446094873023" ovh="58" dps="98" dpstime="51.3244321735169" classe="sha" decurse="0" death="0" />
    <player dmgout="0.0579656106639158" heal="9.96636324442167" name="Naomil" pres="100" dmgin="3.0839482510781" ovh="75" dps="124" dpstime="13.1126873621873" classe="pri" decurse="0" death="0" />
    <player dmgout="0.0356496489826975" heal="5.57324840764331" name="Milledius" pres="100" dmgin="4.00201245807379" ovh="67" dps="132" dpstime="7.50069206533635" classe="pri" decurse="0" death="2" />
    <player dmgout="0" heal="7.68947621023176" name="Hateorade" pres="100" dmgin="2.2184954480115" ovh="65" dps="0" dpstime="0.205638328827575" classe="pal" decurse="0" death="0" />
    <player dmgout="0" heal="18.4227330779055" name="Dernus" pres="100" dmgin="1.86200287494011" ovh="60" dps="0" dpstime="0" classe="sha" decurse="0" death="0" />
    <player dmgout="0" heal="6.78612392317642" name="Cyder" pres="100" dmgin="3.33004312410158" ovh="72" dps="0" dpstime="0" classe="pal" decurse="0" death="0" />
    <player dmgout="0" heal="3.71549893842887" name="Tahonaa" pres="100" dmgin="1.12870148538572" ovh="54" dps="0" dpstime="0" classe="drd" decurse="0" death="1" />
  </raid>
</wws-history>
